LICENSE
README.md
requirements.txt
setup.py
examples/example.jpg
examples/example.py
tf_SmeLU.egg-info/PKG-INFO
tf_SmeLU.egg-info/SOURCES.txt
tf_SmeLU.egg-info/dependency_links.txt
tf_SmeLU.egg-info/requires.txt
tf_SmeLU.egg-info/top_level.txt
tf_smelu/__init__.py
tf_smelu/smelu.py
tf_smelu/__pycache__/smelu.cpython-310.pyc