Metadata-Version: 2.1
Name: tf-SmeLU
Version: 1.0.0
Summary: Tensorflow Smooth ReLU (SmeLU) implementation
Home-page: https://github.com/r3v1/tf-SmeLU
Author: David
Author-email: r3v1@pm.me
License: MIT
Keywords: tensorflow activation smelu
Platform: UNKNOWN
Classifier: Development Status :: 3 - Alpha
Classifier: Intended Audience :: Developers
Classifier: Intended Audience :: Science/Research
Classifier: License :: OSI Approved :: Apache Software License
Classifier: Programming Language :: Python :: 3.8
Classifier: Programming Language :: Python :: 3.9
Classifier: Programming Language :: Python :: 3.10
Classifier: Topic :: Scientific/Engineering
Classifier: Topic :: Scientific/Engineering :: Artificial Intelligence
Classifier: Topic :: Software Development
Classifier: Topic :: Software Development :: Libraries
Classifier: Topic :: Software Development :: Libraries :: Python Modules
Requires-Python: >=3.8
Provides-Extra: matplotlib
License-File: LICENSE
